[
    {
        "title": "Grendel",
        "author": "Gardner, John",
        "cover": "https://i.gr-assets.com/images/S/compressed.photo.goodreads.com/books/1347871284l/676737._SY75_.jpg"
    },
    {
        "title": "The Inner Game of Tennis: The Classic Guide to the Mental Side of Peak Performance",
        "author": "Gallwey, W. Timothy",
        "cover": "https://i.gr-assets.com/images/S/compressed.photo.goodreads.com/books/1427665815l/905._SY75_.jpg"
    },
    {
        "title": "Against Method",
        "author": "Feyerabend, Paul Karl",
        "cover": "https://i.gr-assets.com/images/S/compressed.photo.goodreads.com/books/1373999202l/137979._SY75_.jpg"
    },
    {
        "title": "Germinal",
        "author": "Zola, Émile",
        "cover": "https://i.gr-assets.com/images/S/compressed.photo.goodreads.com/books/1628462562l/28407._SY75_.jpg"
    },
    {
        "title": "Ficciones",
        "author": "Borges, Jorge Luis",
        "cover": "https://i.gr-assets.com/images/S/compressed.photo.goodreads.com/books/1621713120l/426504._SY75_.jpg"
    },
    {
        "title": "The Melancholy of Resistance",
        "author": "Krasznahorkai, László",
        "cover": "https://i.gr-assets.com/images/S/compressed.photo.goodreads.com/books/1656784717l/119512._SY75_.jpg"
    },
    {
        "title": "Philosophy and Simulation: The Emergence of Synthetic Reason",
        "author": "DeLanda, Manuel",
        "cover": "https://i.gr-assets.com/images/S/compressed.photo.goodreads.com/books/1347311133l/10393464._SY75_.jpg"
    },
    {
        "title": "Good Thinking: The Foundations of Probability and Its Applications (Dover Books on Mathematics)",
        "author": "Good, Irving John",
        "cover": "https://i.gr-assets.com/images/S/compressed.photo.goodreads.com/books/1328863167l/6638587._SY75_.jpg"
    },
    {
        "title": "The Diving Bell and the Butterfly",
        "author": "Bauby, Jean-Dominique",
        "cover": "https://i.gr-assets.com/images/S/compressed.photo.goodreads.com/books/1336930564l/193755._SY75_.jpg"
    },
    {
        "title": "Contagious: Why Things Catch On",
        "author": "Berger, Jonah",
        "cover": "https://i.gr-assets.com/images/S/compressed.photo.goodreads.com/books/1376783352l/15801967._SY75_.jpg"
    },
    {
        "title": "The Emotional Brain: The Mysterious Underpinnings of Emotional Life",
        "author": "LeDoux, Joseph E.",
        "cover": "https://i.gr-assets.com/images/S/compressed.photo.goodreads.com/books/1348557712l/780672._SY75_.jpg"
    },
    {
        "title": "Thinking In Systems: A Primer",
        "author": "Meadows, Donella H.",
        "cover": "https://i.gr-assets.com/images/S/compressed.photo.goodreads.com/books/1390169859l/3828902._SY75_.jpg"
    },
    {
        "title": "How to Read a Book: The Classic Guide to Intelligent Reading",
        "author": "Adler, Mortimer J.",
        "cover": "https://i.gr-assets.com/images/S/compressed.photo.goodreads.com/books/1310993739l/567610._SY75_.jpg"
    },
    {
        "title": "The Bed of Procrustes: Philosophical and Practical Aphorisms (Incerto)",
        "author": "Taleb, Nassim Nicholas",
        "cover": "https://i.gr-assets.com/images/S/compressed.photo.goodreads.com/books/1665067245l/9402297._SY75_.jpg"
    },
    {
        "title": "Skin in the Game: The Hidden Asymmetries in Daily Life",
        "author": "Taleb, Nassim Nicholas",
        "cover": "https://i.gr-assets.com/images/S/compressed.photo.goodreads.com/books/1510319798l/36064445._SY75_.jpg"
    },
    {
        "title": "Antifragile: Things That Gain from Disorder",
        "author": "Taleb, Nassim Nicholas",
        "cover": "https://i.gr-assets.com/images/S/compressed.photo.goodreads.com/books/1352422827l/13530973._SY75_.jpg"
    },
    {
        "title": "The Black Swan: The Impact of the Highly Improbable",
        "author": "Taleb, Nassim Nicholas",
        "cover": "https://i.gr-assets.com/images/S/compressed.photo.goodreads.com/books/1386925471l/242472._SY75_.jpg"
    },
    {
        "title": "The Mind is Flat: The Illusion of Mental Depth and The Improvised Mind",
        "author": "Chater, Nick",
        "cover": "https://i.gr-assets.com/images/S/compressed.photo.goodreads.com/books/1515861260l/37926707._SY75_.jpg"
    },
    {
        "title": "Optionality: How to Survive and Thrive in a Volatile World",
        "author": "Meadows, Richard",
        "cover": "https://i.gr-assets.com/images/S/compressed.photo.goodreads.com/books/1678228400l/123202416._SX50_.jpg"
    },
    {
        "title": "Hackers and Painters",
        "author": "Graham, Paul",
        "cover": "https://i.gr-assets.com/images/S/compressed.photo.goodreads.com/books/1348562702l/41793._SY75_.jpg"
    },
    {
        "title": "The Art of Language Invention: From Horse-Lords to Dark Elves to Sand Worms, the Words Behind World-Building",
        "author": "Peterson, David J.",
        "cover": "https://i.gr-assets.com/images/S/compressed.photo.goodreads.com/books/1430758353l/24611649._SY75_.jpg"
    },
    {
        "title": "Against the Gods: The Remarkable Story of Risk",
        "author": "Bernstein, Peter L.",
        "cover": "https://i.gr-assets.com/images/S/compressed.photo.goodreads.com/books/1541411380l/128429._SY75_.jpg"
    },
    {
        "title": "Thing Explainer: Complicated Stuff in Simple Words",
        "author": "Munroe, Randall",
        "cover": "https://i.gr-assets.com/images/S/compressed.photo.goodreads.com/books/1431518396l/25329850._SX50_.jpg"
    },
    {
        "title": "Reality is Broken: Why Games Make Us Better and How They Can Change the World",
        "author": "McGonigal, Jane",
        "cover": "https://i.gr-assets.com/images/S/compressed.photo.goodreads.com/books/1359386702l/7821348._SY75_.jpg"
    },
    {
        "title": "The Bell Curve: Intelligence and Class Structure in American Life",
        "author": "Herrnstein, Richard J.",
        "cover": "https://i.gr-assets.com/images/S/compressed.photo.goodreads.com/books/1388180657l/223556._SY75_.jpg"
    },
    {
        "title": "Good Strategy Bad Strategy: The Difference and Why It Matters",
        "author": "Rumelt, Richard P.",
        "cover": "https://i.gr-assets.com/images/S/compressed.photo.goodreads.com/books/1360570381l/11721966._SY75_.jpg"
    },
    {
        "title": "The Worm at the Core: On the Role of Death in Life",
        "author": "Solomon, Sheldon",
        "cover": "https://i.gr-assets.com/images/S/compressed.photo.goodreads.com/books/1419181981l/22545857._SY75_.jpg"
    },
    {
        "title": "The Wisdom of Crowds",
        "author": "Surowiecki, James",
        "cover": "https://i.gr-assets.com/images/S/compressed.photo.goodreads.com/books/1388211043l/68143._SY75_.jpg"
    },
    {
        "title": "Stop Missing Your Life: How to be Deeply Present in an Un-Present World",
        "author": "Muscara, Cory",
        "cover": "https://i.gr-assets.com/images/S/compressed.photo.goodreads.com/books/1570444134l/45031890._SX50_.jpg"
    },
    {
        "title": "The Essays of Warren Buffett : Lessons for Corporate America",
        "author": "Buffett, Warren",
        "cover": "https://i.gr-assets.com/images/S/compressed.photo.goodreads.com/books/1387742847l/145565._SY75_.jpg"
    },
    {
        "title": "The Folly of Fools: The Logic of Deceit and Self-Deception in Human Life",
        "author": "Trivers, Robert",
        "cover": "https://i.gr-assets.com/images/S/compressed.photo.goodreads.com/books/1320861437l/13033022._SY75_.jpg"
    },
    {
        "title": "The Sovereign Individual: Mastering the Transition to the Information Age",
        "author": "Davidson, James Dale",
        "cover": "https://i.gr-assets.com/images/S/compressed.photo.goodreads.com/books/1388334031l/82256._SY75_.jpg"
    },
    {
        "title": "The Storyteller's Secret: How the World's Most Inspiring Leaders Turn Their Passion Into Performance",
        "author": "Gallo, Carmine",
        "cover": "https://i.gr-assets.com/images/S/compressed.photo.goodreads.com/books/1450039721l/25663767._SY75_.jpg"
    },
    {
        "title": "Thinking in Time: The Uses of History for Decision-Makers",
        "author": "Neustadt, Richard E.",
        "cover": "https://i.gr-assets.com/images/S/compressed.photo.goodreads.com/books/1499643815l/739784._SY75_.jpg"
    },
    {
        "title": "A Conflict of Visions: Ideological Origins of Political Struggles",
        "author": "Sowell, Thomas",
        "cover": "https://i.gr-assets.com/images/S/compressed.photo.goodreads.com/books/1386923639l/3047._SY75_.jpg"
    },
    {
        "title": "How to Make the World Add Up: Ten Rules for Thinking Differently About Numbers",
        "author": "Harford, Tim",
        "cover": "https://i.gr-assets.com/images/S/compressed.photo.goodreads.com/books/1594979690l/54564213._SY75_.jpg"
    },
    {
        "title": "Tools of Titans: The Tactics, Routines, and Habits of Billionaires, Icons, and World-Class Performers",
        "author": "Ferriss, Timothy",
        "cover": "https://i.gr-assets.com/images/S/compressed.photo.goodreads.com/books/1472831109l/31823677._SX50_.jpg"
    },
    {
        "title": "How to Travel With a Salmon & Other Essays",
        "author": "Eco, Umberto",
        "cover": "https://i.gr-assets.com/images/S/compressed.photo.goodreads.com/books/1388192183l/23066._SY75_.jpg"
    },
    {
        "title": "The Gervais Principle: The Complete Series, with a Bonus Essay on Office Space (Ribbonfarm Roughs)",
        "author": "Rao, Venkatesh G.",
        "cover": "https://i.gr-assets.com/images/S/compressed.photo.goodreads.com/books/1601873218l/18581690._SY75_.jpg"
    },
    {
        "title": "Where Is My Flying Car?: A Memoir of Future Past",
        "author": "Hall, J. Storrs",
        "cover": "https://i.gr-assets.com/images/S/compressed.photo.goodreads.com/books/1537823874l/42036377._SY75_.jpg"
    },
    {
        "title": "The Science of Storytelling",
        "author": "Storr, Will",
        "cover": "https://i.gr-assets.com/images/S/compressed.photo.goodreads.com/books/1544377518l/43183121._SY75_.jpg"
    },
    {
        "title": "Words from the Wise: Over 6,000 of the Smartest Things Ever Said",
        "author": "Jarski, Rosemarie",
        "cover": "https://i.gr-assets.com/images/S/compressed.photo.goodreads.com/books/1347523764l/1954195._SX50_.jpg"
    },
    {
        "title": "Tools for Thought: The History and Future of Mind-Expanding Technology",
        "author": "Rheingold, Howard",
        "cover": "https://i.gr-assets.com/images/S/compressed.photo.goodreads.com/books/1387733998l/424084._SY75_.jpg"
    },
    {
        "title": "How to Change Your Mind: What the New Science of Psychedelics Teaches Us About Consciousness, Dying, Addiction, Depression, and Transcendence",
        "author": "Pollan, Michael",
        "cover": "https://i.gr-assets.com/images/S/compressed.photo.goodreads.com/books/1545030338l/36613747._SY75_.jpg"
    },
    {
        "title": "How Not to Be Wrong: The Power of Mathematical Thinking",
        "author": "Ellenberg, Jordan",
        "cover": "https://i.gr-assets.com/images/S/compressed.photo.goodreads.com/books/1387726285l/18693884._SY75_.jpg"
    },
    {
        "title": "The Systems Bible: The Beginner's Guide to Systems Large and Small",
        "author": "Gall, John",
        "cover": "https://i.gr-assets.com/images/S/compressed.photo.goodreads.com/books/1176010078l/583785._SY75_.jpg"
    },
    {
        "title": "Fooled by Randomness: The Hidden Role of Chance in Life and in the Markets (Incerto)",
        "author": "Taleb, Nassim Nicholas",
        "cover": "https://i.gr-assets.com/images/S/compressed.photo.goodreads.com/books/1388180506l/38315._SY75_.jpg"
    },
    {
        "title": "Excellent Sheep: The Miseducation of the American Elite and the Way to a Meaningful Life",
        "author": "Deresiewicz, William",
        "cover": "https://i.gr-assets.com/images/S/compressed.photo.goodreads.com/books/1408319760l/18775383._SX50_.jpg"
    },
    {
        "title": "I Am a Strange Loop",
        "author": "Hofstadter, Douglas R.",
        "cover": "https://i.gr-assets.com/images/S/compressed.photo.goodreads.com/books/1442775722l/123471._SX50_.jpg"
    },
    {
        "title": "Gödel, Escher, Bach: An Eternal Golden Braid",
        "author": "Hofstadter, Douglas R.",
        "cover": "https://i.gr-assets.com/images/S/compressed.photo.goodreads.com/books/1547125681l/24113._SY75_.jpg"
    },
    {
        "title": "Demonology (Otherworld Stories, #0.05)",
        "author": "Armstrong, Kelley",
        "cover": "https://i.gr-assets.com/images/S/compressed.photo.goodreads.com/books/1297202662l/10417468._SX50_.jpg"
    },
    {
        "title": "The Quest of the Simple Life",
        "author": "Dawson, William James",
        "cover": "https://i.gr-assets.com/images/S/compressed.photo.goodreads.com/books/1384804422l/18670760._SY75_.jpg"
    },
    {
        "title": "The Beginning of Infinity: Explanations That Transform the World",
        "author": "Deutsch, David",
        "cover": "https://i.gr-assets.com/images/S/compressed.photo.goodreads.com/books/1311705051l/10483171._SY75_.jpg"
    },
    {
        "title": "The Fabric of Reality: The Science of Parallel Universes--and Its Implications",
        "author": "Deutsch, David",
        "cover": "https://i.gr-assets.com/images/S/compressed.photo.goodreads.com/books/1348344833l/177068._SY75_.jpg"
    },
    {
        "title": "The Sword and the Shield: The Mitrokhin Archive and the Secret History of the KGB",
        "author": "Andrew, Christopher",
        "cover": "https://i.gr-assets.com/images/S/compressed.photo.goodreads.com/books/1440642067l/10756._SX50_.jpg"
    },
    {
        "title": "Just the Arguments",
        "author": "Bruce, Michael",
        "cover": "https://i.gr-assets.com/images/S/compressed.photo.goodreads.com/books/1348524451l/12838972._SY75_.jpg"
    },
    {
        "title": "Bronze Age Mindset",
        "author": "Bronze Age Pervert",
        "cover": "https://i.gr-assets.com/images/S/compressed.photo.goodreads.com/books/1528212142l/40388177._SY75_.jpg"
    },
    {
        "title": "Breaking the Spell: Religion as a Natural Phenomenon",
        "author": "Dennett, Daniel C.",
        "cover": "https://i.gr-assets.com/images/S/compressed.photo.goodreads.com/books/1406403613l/2067._SY75_.jpg"
    },
    {
        "title": "Surrounded by Idiots",
        "author": "Erikson, Thomas",
        "cover": "https://i.gr-assets.com/images/S/compressed.photo.goodreads.com/books/1583763517l/39101777._SX50_.jpg"
    },
    {
        "title": "Venture Deals: Be Smarter Than Your Lawyer and Venture Capitalist",
        "author": "Feld, Brad",
        "cover": "https://i.gr-assets.com/images/S/compressed.photo.goodreads.com/books/1356089559l/11865558._SY75_.jpg"
    },
    {
        "title": "The Paradox of Choice: Why More Is Less",
        "author": "Schwartz, Barry",
        "cover": "https://i.gr-assets.com/images/S/compressed.photo.goodreads.com/books/1410138134l/10639._SY75_.jpg"
    },
    {
        "title": "Black Box Thinking: Why Some People Never Learn from Their Mistakes - But Some Do",
        "author": "Syed, Matthew",
        "cover": "https://i.gr-assets.com/images/S/compressed.photo.goodreads.com/books/1442833652l/24611735._SY75_.jpg"
    },
    {
        "title": "The Art of Strategy: A Game Theorist's Guide to Success in Business and Life",
        "author": "Dixit, Avinash K.",
        "cover": "https://i.gr-assets.com/images/S/compressed.photo.goodreads.com/books/1347728926l/2423424._SY75_.jpg"
    },
    {
        "title": "Thinking Strategically: The Competitive Edge in Business, Politics, and Everyday Life (Norton Paperback)",
        "author": "Dixit, Avinash K.",
        "cover": "https://i.gr-assets.com/images/S/compressed.photo.goodreads.com/books/1347324446l/103592._SY75_.jpg"
    },
    {
        "title": "Alchemy: The Surprising Power of Ideas That Don't Make Sense",
        "author": "Sutherland, Rory",
        "cover": "https://i.gr-assets.com/images/S/compressed.photo.goodreads.com/books/1549539347l/26210508._SX50_.jpg"
    },
    {
        "title": "Order without Design: How Markets Shape Cities (Mit Press)",
        "author": "Bertaud, Alain",
        "cover": "https://i.gr-assets.com/images/S/compressed.photo.goodreads.com/books/1544515502l/39644188._SX50_.jpg"
    },
    {
        "title": "Originals: How Non-Conformists Move the World",
        "author": "Grant, Adam M.",
        "cover": "https://i.gr-assets.com/images/S/compressed.photo.goodreads.com/books/1445791874l/25614523._SY75_.jpg"
    },
    {
        "title": "Seeing Like a State: How Certain Schemes to Improve the Human Condition Have Failed",
        "author": "Scott, James C.",
        "cover": "https://i.gr-assets.com/images/S/compressed.photo.goodreads.com/books/1563058549l/20186._SY75_.jpg"
    },
    {
        "title": "Infinity and the Mind: The Science and Philosophy of the Infinite (Princeton Science Library)",
        "author": "Rucker, Rudy",
        "cover": "https://i.gr-assets.com/images/S/compressed.photo.goodreads.com/books/1347508303l/274050._SY75_.jpg"
    },
    {
        "title": "The Innovator's Dilemma: The Revolutionary Book that Will Change the Way You Do Business",
        "author": "Christensen, Clayton M.",
        "cover": "https://i.gr-assets.com/images/S/compressed.photo.goodreads.com/books/1347654027l/2615._SY75_.jpg"
    },
    {
        "title": "The Information: A History, a Theory, a Flood",
        "author": "Gleick, James",
        "cover": "https://i.gr-assets.com/images/S/compressed.photo.goodreads.com/books/1348046486l/8701960._SX50_.jpg"
    },
    {
        "title": "The Why Axis: Hidden Motives and The Undiscovered Economics of Everyday Life",
        "author": "Gneezy, Uri",
        "cover": "https://i.gr-assets.com/images/S/compressed.photo.goodreads.com/books/1473012091l/17693458._SX50_.jpg"
    },
    {
        "title": "The World Beyond Your Head: On Becoming an Individual in an Age of Distraction",
        "author": "Crawford, Matthew B.",
        "cover": "https://i.gr-assets.com/images/S/compressed.photo.goodreads.com/books/1416448116l/22237171._SX50_.jpg"
    },
    {
        "title": "The Almanack of Naval Ravikant: A Guide to Wealth and Happiness",
        "author": "Jorgenson, Eric",
        "cover": "https://i.gr-assets.com/images/S/compressed.photo.goodreads.com/books/1598011736l/54898389._SY75_.jpg"
    },
    {
        "title": "Grit: The Power of Passion and Perseverance",
        "author": "Duckworth, Angela",
        "cover": "https://i.gr-assets.com/images/S/compressed.photo.goodreads.com/books/1632024090l/27213329._SY75_.jpg"
    },
    {
        "title": "My Years with General Motors",
        "author": "Sloan, Alfred P.",
        "cover": "https://i.gr-assets.com/images/S/compressed.photo.goodreads.com/books/1347715286l/275912._SY75_.jpg"
    },
    {
        "title": "Universal Principles of Design",
        "author": "Lidwell, William",
        "cover": "https://i.gr-assets.com/images/S/compressed.photo.goodreads.com/books/1328754391l/130730._SX50_.jpg"
    },
    {
        "title": "An Introduction to Cybernetics",
        "author": "Ashby, William Ross",
        "cover": "https://i.gr-assets.com/images/S/compressed.photo.goodreads.com/books/1345703021l/583911._SX50_.jpg"
    },
    {
        "title": "Stastical Methods as Applied to Economics, Business, Psychology, Education, ; Biology",
        "author": "Arkin, Herbert",
        "cover": "https://s.gr-assets.com/assets/nophoto/book/50x75-a91bf249278a81aabab721ef782c4a74.png"
    },
    {
        "title": "So You Wanna Be an Embedded Engineer: The Guide to Embedded Engineering, From Consultancy to the Corporate Ladder (Embedded Technology) by Lewin Edwards Lewin Edwards is an embedded engineer with over 15 years experience designing embedded systems hard...",
        "author": "Edwards, Lewin",
        "cover": "https://i.gr-assets.com/images/S/compressed.photo.goodreads.com/books/1698071717l/160317622._SX50_.jpg"
    },
    {
        "title": "Saturn V Flight Manual",
        "author": "NASA",
        "cover": "https://i.gr-assets.com/images/S/compressed.photo.goodreads.com/books/1347396065l/14647646._SX50_.jpg"
    },
    {
        "title": "Ubik",
        "author": "Dick, Philip K.",
        "cover": "https://i.gr-assets.com/images/S/compressed.photo.goodreads.com/books/1327995569l/22590._SY75_.jpg"
    },
    {
        "title": "Six Wakes",
        "author": "Lafferty, Mur",
        "cover": "https://i.gr-assets.com/images/S/compressed.photo.goodreads.com/books/1483175828l/28962996._SY75_.jpg"
    },
    {
        "title": "Stranger in a Strange Land",
        "author": "Heinlein, Robert A.",
        "cover": "https://i.gr-assets.com/images/S/compressed.photo.goodreads.com/books/1156897088l/350._SY75_.jpg"
    },
    {
        "title": "Farenheit 451",
        "author": "Bradbury, Ray",
        "cover": "https://i.gr-assets.com/images/S/compressed.photo.goodreads.com/books/1608059811l/56302573._SY75_.jpg"
    },
    {
        "title": "Profiles of the Future: An Inquiry into the Limits of the Possible",
        "author": "Clarke, Arthur C.",
        "cover": "https://i.gr-assets.com/images/S/compressed.photo.goodreads.com/books/1172363833l/169258._SY75_.jpg"
    },
    {
        "title": "Blindsight (Firefall, #1)",
        "author": "Watts, Peter",
        "cover": "https://i.gr-assets.com/images/S/compressed.photo.goodreads.com/books/1386924412l/48484._SX50_.jpg"
    },
    {
        "title": "Snow Crash",
        "author": "Stephenson, Neal",
        "cover": "https://i.gr-assets.com/images/S/compressed.photo.goodreads.com/books/1589842551l/40651883._SX50_.jpg"
    },
    {
        "title": "Fall; or, Dodge in Hell (Crypto, #3)",
        "author": "Stephenson, Neal",
        "cover": "https://i.gr-assets.com/images/S/compressed.photo.goodreads.com/books/1548719156l/41824495._SY75_.jpg"
    },
    {
        "title": "The Diamond Age: Or, a Young Lady's Illustrated Primer",
        "author": "Stephenson, Neal",
        "cover": "https://i.gr-assets.com/images/S/compressed.photo.goodreads.com/books/1388180931l/827._SY75_.jpg"
    },
    {
        "title": "Consider Phlebas (Culture, #1)",
        "author": "Banks, Iain M.",
        "cover": "https://i.gr-assets.com/images/S/compressed.photo.goodreads.com/books/1327951890l/8935689._SY75_.jpg"
    },
    {
        "title": "Island",
        "author": "Huxley, Aldous",
        "cover": "https://i.gr-assets.com/images/S/compressed.photo.goodreads.com/books/1375947541l/5130._SY75_.jpg"
    },
    {
        "title": "Permutation City",
        "author": "Egan, Greg",
        "cover": "https://i.gr-assets.com/images/S/compressed.photo.goodreads.com/books/1287341300l/156784._SY75_.jpg"
    },
    {
        "title": "Diaspora",
        "author": "Egan, Greg",
        "cover": "https://i.gr-assets.com/images/S/compressed.photo.goodreads.com/books/1172264162l/156785._SY75_.jpg"
    },
    {
        "title": "Earth",
        "author": "Brin, David",
        "cover": "https://i.gr-assets.com/images/S/compressed.photo.goodreads.com/books/1347288634l/96471._SY75_.jpg"
    },
    {
        "title": "Flowers for Algernon",
        "author": "Keyes, Daniel",
        "cover": "https://i.gr-assets.com/images/S/compressed.photo.goodreads.com/books/1689071681l/18373._SY75_.jpg"
    },
    {
        "title": "Contact",
        "author": "Sagan, Carl",
        "cover": "https://i.gr-assets.com/images/S/compressed.photo.goodreads.com/books/1602082958l/61666._SY75_.jpg"
    },
    {
        "title": "The Sentinel",
        "author": "Clarke, Arthur C.",
        "cover": "https://i.gr-assets.com/images/S/compressed.photo.goodreads.com/books/1375814785l/149070._SY75_.jpg"
    },
    {
        "title": "Stories of Your Life and Others",
        "author": "Chiang, Ted",
        "cover": "https://i.gr-assets.com/images/S/compressed.photo.goodreads.com/books/1356138316l/223380._SY75_.jpg"
    },
    {
        "title": "Childhood’s End",
        "author": "Clarke, Arthur C.",
        "cover": "https://i.gr-assets.com/images/S/compressed.photo.goodreads.com/books/1320552628l/414999._SY75_.jpg"
    },
    {
        "title": "Project Hail Mary",
        "author": "Weir, Andy",
        "cover": "https://i.gr-assets.com/images/S/compressed.photo.goodreads.com/books/1597695864l/54493401._SY75_.jpg"
    },
    {
        "title": "Artemis",
        "author": "Weir, Andy",
        "cover": "https://i.gr-assets.com/images/S/compressed.photo.goodreads.com/books/1494273579l/34928122._SY75_.jpg"
    },
    {
        "title": "Brave New World",
        "author": "Huxley, Aldous",
        "cover": "https://i.gr-assets.com/images/S/compressed.photo.goodreads.com/books/1575509280l/5129._SY75_.jpg"
    },
    {
        "title": "The Three-Body Problem (Remembrance of Earth’s Past, #1)",
        "author": "Liu, Cixin",
        "cover": "https://i.gr-assets.com/images/S/compressed.photo.goodreads.com/books/1415428227l/20518872._SY75_.jpg"
    },
    {
        "title": "Liftoff: Elon Musk and the Desperate Early Days That Launched SpaceX",
        "author": "Berger, Eric",
        "cover": "https://i.gr-assets.com/images/S/compressed.photo.goodreads.com/books/1602088633l/53402132._SY75_.jpg"
    },
    {
        "title": "Evolution in Four Dimensions: Genetic, Epigenetic, Behavioral, And Symbolic Variation in the History of Life (Life And Mind: Philosophical Issues in Biology And Philosophy Series)",
        "author": "Jablonka, Eva",
        "cover": "https://i.gr-assets.com/images/S/compressed.photo.goodreads.com/books/1562985958l/747570._SY75_.jpg"
    },
    {
        "title": "How Innovation Works: Serendipity, Energy and the Saving of Time",
        "author": "Ridley, Matt",
        "cover": "https://i.gr-assets.com/images/S/compressed.photo.goodreads.com/books/1577249358l/52219273._SY75_.jpg"
    },
    {
        "title": "Chaos: Making a New Science",
        "author": "Gleick, James",
        "cover": "https://i.gr-assets.com/images/S/compressed.photo.goodreads.com/books/1327941595l/64582._SY75_.jpg"
    },
    {
        "title": "Elements of Mathematics: From Euclid to Gödel",
        "author": "Stillwell, John",
        "cover": "https://i.gr-assets.com/images/S/compressed.photo.goodreads.com/books/1574745771l/27311989._SY75_.jpg"
    },
    {
        "title": "The Goldilocks Enigma: Why Is the Universe Just Right for Life?",
        "author": "Davies, Paul C.W.",
        "cover": "https://i.gr-assets.com/images/S/compressed.photo.goodreads.com/books/1347935311l/817511._SY75_.jpg"
    },
    {
        "title": "The Mind of God: The Scientific Basis for a Rational World",
        "author": "Davies, Paul C.W.",
        "cover": "https://i.gr-assets.com/images/S/compressed.photo.goodreads.com/books/1348647530l/137797._SY75_.jpg"
    },
    {
        "title": "Cycles of Time: An Extraordinary New View of the Universe",
        "author": "Penrose, Roger",
        "cover": "https://i.gr-assets.com/images/S/compressed.photo.goodreads.com/books/1320506839l/7947434._SY75_.jpg"
    },
    {
        "title": "The Age of Spiritual Machines",
        "author": "Kurzweil, Ray",
        "cover": "https://i.gr-assets.com/images/S/compressed.photo.goodreads.com/books/1309284708l/83533._SX50_.jpg"
    },
    {
        "title": "The Road to Reality: A Complete Guide to the Laws of the Universe",
        "author": "Penrose, Roger",
        "cover": "https://i.gr-assets.com/images/S/compressed.photo.goodreads.com/books/1386924912l/10638._SX50_.jpg"
    },
    {
        "title": "The Half-life of Facts: Why Everything We Know Has an Expiration Date",
        "author": "Arbesman, Samuel",
        "cover": "https://i.gr-assets.com/images/S/compressed.photo.goodreads.com/books/1355066251l/13588433._SY75_.jpg"
    },
    {
        "title": "Pihkal: A Chemical Love Story",
        "author": "Shulgin, Alexander",
        "cover": "https://i.gr-assets.com/images/S/compressed.photo.goodreads.com/books/1298130682l/886113._SY75_.jpg"
    },
    {
        "title": "The Order of Time",
        "author": "Rovelli, Carlo",
        "cover": "https://i.gr-assets.com/images/S/compressed.photo.goodreads.com/books/1516424407l/36442813._SY75_.jpg"
    },
    {
        "title": "The Periodic Table",
        "author": "Levi, Primo",
        "cover": "https://i.gr-assets.com/images/S/compressed.photo.goodreads.com/books/1403193930l/427282._SY75_.jpg"
    },
    {
        "title": "This Idea Must Die: Scientific Theories That Are Blocking Progress (Edge Question Series)",
        "author": "Brockman, John",
        "cover": "https://i.gr-assets.com/images/S/compressed.photo.goodreads.com/books/1418771663l/22477307._SY75_.jpg"
    },
    {
        "title": "The Psychological Construction of Emotion",
        "author": "Barrett, Lisa Feldman",
        "cover": "https://i.gr-assets.com/images/S/compressed.photo.goodreads.com/books/1393958478l/20694768._SX50_.jpg"
    },
    {
        "title": "The Power of Now: A Guide to Spiritual Enlightenment",
        "author": "Tolle, Eckhart",
        "cover": "https://i.gr-assets.com/images/S/compressed.photo.goodreads.com/books/1689947880l/6708._SY75_.jpg"
    },
    {
        "title": "The Handbook of Evolutionary Psychology",
        "author": "Buss, David M.",
        "cover": "https://i.gr-assets.com/images/S/compressed.photo.goodreads.com/books/1348094478l/663088._SY75_.jpg"
    },
    {
        "title": "Willpower: Rediscovering the Greatest Human Strength",
        "author": "Baumeister, Roy F.",
        "cover": "https://i.gr-assets.com/images/S/compressed.photo.goodreads.com/books/1347857263l/11104933._SY75_.jpg"
    },
    {
        "title": "The Psychopathology of Everyday Life",
        "author": "Freud, Sigmund",
        "cover": "https://i.gr-assets.com/images/S/compressed.photo.goodreads.com/books/1348267537l/132449._SX50_.jpg"
    },
    {
        "title": "Spent: Sex, Evolution, and Consumer Behavior",
        "author": "Miller, Geoffrey",
        "cover": "https://i.gr-assets.com/images/S/compressed.photo.goodreads.com/books/1442276223l/6283340._SY75_.jpg"
    },
    {
        "title": "Influence: The Psychology of Persuasion",
        "author": "Cialdini, Robert B.",
        "cover": "https://i.gr-assets.com/images/S/compressed.photo.goodreads.com/books/1391026083l/28815._SY75_.jpg"
    },
    {
        "title": "Identity Theory",
        "author": "Burke, Peter J.",
        "cover": "https://i.gr-assets.com/images/S/compressed.photo.goodreads.com/books/1348819332l/6917010._SX50_.jpg"
    },
    {
        "title": "Civilization and Its Discontents",
        "author": "Freud, Sigmund",
        "cover": "https://i.gr-assets.com/images/S/compressed.photo.goodreads.com/books/1438544596l/357636._SY75_.jpg"
    },
    {
        "title": "Memories, Dreams, Reflections",
        "author": "Jung, Carl",
        "cover": "https://i.gr-assets.com/images/S/compressed.photo.goodreads.com/books/1348081175l/612188._SY75_.jpg"
    },
    {
        "title": "Punished by Rewards: The Trouble with Gold Stars, Incentive Plans, A's, Praise and Other Bribes",
        "author": "Kohn, Alfie",
        "cover": "https://i.gr-assets.com/images/S/compressed.photo.goodreads.com/books/1422456630l/541132._SY75_.jpg"
    },
    {
        "title": "The Power of the Powerless",
        "author": "Havel, Václav",
        "cover": "https://i.gr-assets.com/images/S/compressed.photo.goodreads.com/books/1328040320l/384786._SY75_.jpg"
    },
    {
        "title": "The Kill Chain: How Emerging Technologies Threaten America's Military Dominance",
        "author": "Brose, Christian",
        "cover": "https://i.gr-assets.com/images/S/compressed.photo.goodreads.com/books/1576011429l/51338665._SX50_SY75_.jpg"
    },
    {
        "title": "Makers of Modern Strategy from Machiavelli to the Nuclear Age",
        "author": "Paret, Peter",
        "cover": "https://i.gr-assets.com/images/S/compressed.photo.goodreads.com/books/1348718160l/833962._SY75_.jpg"
    },
    {
        "title": "Rise and Kill First: The Secret History of Israel's Targeted Assassinations",
        "author": "Bergman, Ronen",
        "cover": "https://i.gr-assets.com/images/S/compressed.photo.goodreads.com/books/1495743181l/33598223._SY75_.jpg"
    },
    {
        "title": "The End of the World Is Just the Beginning: Mapping the Collapse of Globalization",
        "author": "Zeihan, Peter",
        "cover": "https://i.gr-assets.com/images/S/compressed.photo.goodreads.com/books/1639948123l/58782897._SY75_.jpg"
    },
    {
        "title": "The Reckless Mind: Intellectuals in Politics",
        "author": "Lilla, Mark",
        "cover": "https://i.gr-assets.com/images/S/compressed.photo.goodreads.com/books/1320440334l/422716._SY75_.jpg"
    },
    {
        "title": "The Fifth Risk: Undoing Democracy",
        "author": "Lewis, Michael",
        "cover": "https://i.gr-assets.com/images/S/compressed.photo.goodreads.com/books/1562687004l/46266188._SY75_.jpg"
    },
    {
        "title": "Legitimacy: The Right to Rule in a Wanton World",
        "author": "Applbaum, Arthur Isak",
        "cover": "https://i.gr-assets.com/images/S/compressed.photo.goodreads.com/books/1569891268l/40000416._SY75_.jpg"
    },
    {
        "title": "Intelligence in War: Knowledge of the Enemy from Napoleon to Al-Qaeda",
        "author": "Keegan, John",
        "cover": "https://i.gr-assets.com/images/S/compressed.photo.goodreads.com/books/1386921396l/55195._SX50_.jpg"
    },
    {
        "title": "The Complete Works of John Adams: Autobiography, Discourses On Davila, Essays On The Constitution, Essays And Controversial Papers Of The Revolution, Autobiography ... (11 Books With Active Table of Contents)",
        "author": "Adams, John",
        "cover": "https://i.gr-assets.com/images/S/compressed.photo.goodreads.com/books/1393090607l/20886231._SX50_.jpg"
    },
    {
        "title": "Hegarty on Creativity: There Are No Rules",
        "author": "Hegarty, John",
        "cover": "https://i.gr-assets.com/images/S/compressed.photo.goodreads.com/books/1381286504l/18474153._SY75_.jpg"
    },
    {
        "title": "The Prize: The Epic Quest for Oil, Money, and Power",
        "author": "Yergin, Daniel",
        "cover": "https://i.gr-assets.com/images/S/compressed.photo.goodreads.com/books/1403025725l/169354._SY75_.jpg"
    },
    {
        "title": "Chimpanzee Politics: Power and Sex among Apes",
        "author": "de Waal, Frans",
        "cover": "https://i.gr-assets.com/images/S/compressed.photo.goodreads.com/books/1347968895l/389530._SX50_.jpg"
    },
    {
        "title": "The Dictator's Handbook: Why Bad Behavior Is Almost Always Good Politics",
        "author": "Mesquita, Bruce Bueno De",
        "cover": "https://i.gr-assets.com/images/S/compressed.photo.goodreads.com/books/1328737207l/11612989._SY75_.jpg"
    },
    {
        "title": "Belt and Road: A Chinese World Order",
        "author": "Maçães, Bruno",
        "cover": "https://i.gr-assets.com/images/S/compressed.photo.goodreads.com/books/1534589200l/41213288._SY75_.jpg"
    },
    {
        "title": "The Odyssey of Homer",
        "author": "Vandiver, Elizabeth",
        "cover": "https://i.gr-assets.com/images/S/compressed.photo.goodreads.com/books/1502134935l/2523661._SX50_.jpg"
    },
    {
        "title": "Madhushaala (HINDI)",
        "author": "Bachchan, Harivansh Rai",
        "cover": "https://s.gr-assets.com/assets/nophoto/book/50x75-a91bf249278a81aabab721ef782c4a74.png"
    },
    {
        "title": "A Tenth of a Second: A History",
        "author": "Canales, Jimena",
        "cover": "https://i.gr-assets.com/images/S/compressed.photo.goodreads.com/books/1347906454l/12788070._SX50_.jpg"
    },
    {
        "title": "Trick or Truth?: The Mysterious Connection Between Physics and Mathematics (The Frontiers Collection)",
        "author": "Aguirre, Anthony",
        "cover": "https://i.gr-assets.com/images/S/compressed.photo.goodreads.com/books/1456691881l/27764046._SY75_.jpg"
    },
    {
        "title": "Knowledge And Decisions",
        "author": "Sowell, Thomas",
        "cover": "https://i.gr-assets.com/images/S/compressed.photo.goodreads.com/books/1386921344l/3042._SY75_.jpg"
    },
    {
        "title": "The One by Whom Scandal Comes",
        "author": "Girard, René",
        "cover": "https://i.gr-assets.com/images/S/compressed.photo.goodreads.com/books/1401493820l/22379506._SY75_.jpg"
    },
    {
        "title": "The Hedgehog and the Fox: An Essay on Tolstoy's View of History",
        "author": "Berlin, Isaiah",
        "cover": "https://i.gr-assets.com/images/S/compressed.photo.goodreads.com/books/1344761981l/87436._SY75_.jpg"
    },
    {
        "title": "The State and Revolution",
        "author": "Lenin, Vladimir",
        "cover": "https://i.gr-assets.com/images/S/compressed.photo.goodreads.com/books/1358889486l/179612._SY75_.jpg"
    },
    {
        "title": "Tower of Babel: The Evidence Against the New Creationism (A Bradford Book)",
        "author": "Pennock, Robert T.",
        "cover": "https://i.gr-assets.com/images/S/compressed.photo.goodreads.com/books/1347593290l/60413._SX50_.jpg"
    },
    {
        "title": "Proust: A collection of critical essays",
        "author": "Girard, René",
        "cover": "https://s.gr-assets.com/assets/nophoto/book/50x75-a91bf249278a81aabab721ef782c4a74.png"
    },
    {
        "title": "Beyond Good and Evil",
        "author": "Nietzsche, Friedrich",
        "cover": "https://i.gr-assets.com/images/S/compressed.photo.goodreads.com/books/1388607391l/12321._SY75_.jpg"
    },
    {
        "title": "The Complete Essays",
        "author": "Montaigne, Michel de",
        "cover": "https://i.gr-assets.com/images/S/compressed.photo.goodreads.com/books/1657542435l/30735._SY75_.jpg"
    },
    {
        "title": "Miyamoto Musashi: His Life and Writings",
        "author": "Tokitsu, Kenji",
        "cover": "https://i.gr-assets.com/images/S/compressed.photo.goodreads.com/books/1386912543l/198281._SY75_.jpg"
    },
    {
        "title": "The Master and Margarita",
        "author": "Bulgakov, Mikhail",
        "cover": "https://i.gr-assets.com/images/S/compressed.photo.goodreads.com/books/1327867963l/117833._SY75_.jpg"
    },
    {
        "title": "Make It Stick: The Science of Successful Learning",
        "author": "Brown, Peter C.",
        "cover": "https://i.gr-assets.com/images/S/compressed.photo.goodreads.com/books/1631768711l/18770267._SY75_.jpg"
    },
    {
        "title": "The Constitution of Knowledge: A Defense of Truth",
        "author": "Rauch, Jonathan",
        "cover": "https://i.gr-assets.com/images/S/compressed.photo.goodreads.com/books/1623666829l/54616040._SX50_.jpg"
    },
    {
        "title": "Cities",
        "author": "Reader, John",
        "cover": "https://i.gr-assets.com/images/S/compressed.photo.goodreads.com/books/1320425532l/269449._SY75_.jpg"
    },
    {
        "title": "Água Viva",
        "author": "Lispector, Clarice",
        "cover": "https://i.gr-assets.com/images/S/compressed.photo.goodreads.com/books/1655722688l/13082435._SY75_.jpg"
    },
    {
        "title": "The Essays",
        "author": "Bacon, Francis",
        "cover": "https://i.gr-assets.com/images/S/compressed.photo.goodreads.com/books/1537977650l/677923._SY75_.jpg"
    },
    {
        "title": "Awareness: The Perils and Opportunities of Reality",
        "author": "Mello, Anthony de",
        "cover": "https://i.gr-assets.com/images/S/compressed.photo.goodreads.com/books/1440859557l/94318._SY75_.jpg"
    },
    {
        "title": "The Myth of Sisyphus and Other Essays",
        "author": "Camus, Albert",
        "cover": "https://i.gr-assets.com/images/S/compressed.photo.goodreads.com/books/1533718219l/11987._SY75_.jpg"
    },
    {
        "title": "The Book: On the Taboo Against Knowing Who You Are",
        "author": "Watts, Alan W.",
        "cover": "https://i.gr-assets.com/images/S/compressed.photo.goodreads.com/books/1403166178l/60551._SY75_.jpg"
    },
    {
        "title": "Questioning the Foundations of Physics: Which of Our Fundamental Assumptions Are Wrong? (The Frontiers Collection)",
        "author": "Aguirre, Anthony",
        "cover": "https://i.gr-assets.com/images/S/compressed.photo.goodreads.com/books/1422812766l/24791293._SY75_.jpg"
    },
    {
        "title": "Utopia for Realists: How We Can Build the Ideal World",
        "author": "Bregman, Rutger",
        "cover": "https://i.gr-assets.com/images/S/compressed.photo.goodreads.com/books/1618785125l/40876575._SX50_.jpg"
    },
    {
        "title": "Tractatus Logico-Philosophicus",
        "author": "Wittgenstein, Ludwig",
        "cover": "https://i.gr-assets.com/images/S/compressed.photo.goodreads.com/books/1396830687l/12075._SY75_.jpg"
    },
    {
        "title": "Naming and Necessity",
        "author": "Kripke, Saul A.",
        "cover": "https://i.gr-assets.com/images/S/compressed.photo.goodreads.com/books/1386924258l/276249._SY75_.jpg"
    },
    {
        "title": "Bitter Brew: The Rise and Fall of Anheuser-Busch and America's Kings of Beer",
        "author": "Knoedelseder, William",
        "cover": "https://i.gr-assets.com/images/S/compressed.photo.goodreads.com/books/1353474683l/13622134._SY75_.jpg"
    },
    {
        "title": "City of Djinns: A Year in Delhi",
        "author": "Dalrymple, William",
        "cover": "https://i.gr-assets.com/images/S/compressed.photo.goodreads.com/books/1677706997l/124430._SY75_.jpg"
    },
    {
        "title": "The History and the Life of Chinggis Khan: The Secret History of the Mongols",
        "author": "Onon, Urgunge",
        "cover": "https://i.gr-assets.com/images/S/compressed.photo.goodreads.com/books/1238433893l/679544._SX50_.jpg"
    },
    {
        "title": "The Secret History of the Mongol Queens: How the Daughters of Genghis Khan Rescued His Empire",
        "author": "Weatherford, Jack",
        "cover": "https://i.gr-assets.com/images/S/compressed.photo.goodreads.com/books/1320410503l/6648001._SY75_.jpg"
    },
    {
        "title": "The Theory That Would Not Die: How Bayes' Rule Cracked the Enigma Code, Hunted Down Russian Submarines, and Emerged Triumphant from Two Centuries of Controversy",
        "author": "McGrayne, Sharon Bertsch",
        "cover": "https://i.gr-assets.com/images/S/compressed.photo.goodreads.com/books/1328848187l/10672848._SY75_.jpg"
    },
    {
        "title": "The Splendid and the Vile: A Saga of Churchill, Family, and Defiance During the Blitz",
        "author": "Larson, Erik",
        "cover": "https://i.gr-assets.com/images/S/compressed.photo.goodreads.com/books/1567638164l/51187948._SX50_SY75_.jpg"
    },
    {
        "title": "The Enlightened Economy: An Economic History of Britain 1700-1850 (The New Economic History of Britain seri)",
        "author": "Mokyr, Joel",
        "cover": "https://i.gr-assets.com/images/S/compressed.photo.goodreads.com/books/1264957267l/7146167._SY75_.jpg"
    },
    {
        "title": "The True History of the American Revolution",
        "author": "Fisher, Sydney George",
        "cover": "https://i.gr-assets.com/images/S/compressed.photo.goodreads.com/books/1438406215l/25843585._SY75_.jpg"
    },
    {
        "title": "The Clash of Civilizations and the Remaking of World Order",
        "author": "Huntington, Samuel P.",
        "cover": "https://i.gr-assets.com/images/S/compressed.photo.goodreads.com/books/1338424958l/413179._SY75_.jpg"
    },
    {
        "title": "Dongri To Dubai : Six Decades of The Mumbai Mafia",
        "author": "Zaidi, S. Hussain",
        "cover": "https://i.gr-assets.com/images/S/compressed.photo.goodreads.com/books/1338160153l/13637470._SY75_.jpg"
    },
    {
        "title": "Merchants of Doubt: How a Handful of Scientists Obscured the Truth on Issues from Tobacco Smoke to Global Warming",
        "author": "Oreskes, Naomi",
        "cover": "https://i.gr-assets.com/images/S/compressed.photo.goodreads.com/books/1316131273l/7799004._SY75_.jpg"
    },
    {
        "title": "The Great Influenza: The Story of the Deadliest Pandemic in History",
        "author": "Barry, John M.",
        "cover": "https://i.gr-assets.com/images/S/compressed.photo.goodreads.com/books/1386924908l/29036._SY75_.jpg"
    },
    {
        "title": "Guns, Germs, and Steel: The Fates of Human Societies",
        "author": "Diamond, Jared",
        "cover": "https://i.gr-assets.com/images/S/compressed.photo.goodreads.com/books/1453215833l/1842._SY75_.jpg"
    },
    {
        "title": "The Art of Warfare in the Age of Napoleon",
        "author": "Rothenberg, Gunther E.",
        "cover": "https://i.gr-assets.com/images/S/compressed.photo.goodreads.com/books/1387711077l/1337176._SY75_.jpg"
    },
    {
        "title": "Essence of Decision: Explaining the Cuban Missile Crisis",
        "author": "Allison, Graham T.",
        "cover": "https://i.gr-assets.com/images/S/compressed.photo.goodreads.com/books/1348007950l/418380._SY75_.jpg"
    },
    {
        "title": "The Philosophy of History",
        "author": "Hegel, Georg Wilhelm Friedrich",
        "cover": "https://i.gr-assets.com/images/S/compressed.photo.goodreads.com/books/1328864554l/25241._SY75_.jpg"
    },
    {
        "title": "The Big Change: America Transforms Itself, 1900-50",
        "author": "Allen, Frederick Lewis",
        "cover": "https://i.gr-assets.com/images/S/compressed.photo.goodreads.com/books/1348527951l/2079974._SY75_.jpg"
    },
    {
        "title": "Fingerprints of the Gods: The Evidence of Earth's Lost Civilization",
        "author": "Hancock, Graham",
        "cover": "https://i.gr-assets.com/images/S/compressed.photo.goodreads.com/books/1403173617l/53325._SY75_.jpg"
    },
    {
        "title": "Man, Machines, and Modern Times",
        "author": "Morison, Elting E.",
        "cover": "https://s.gr-assets.com/assets/nophoto/book/50x75-a91bf249278a81aabab721ef782c4a74.png"
    },
    {
        "title": "Life in Code: A Personal History of Technology",
        "author": "Ullman, Ellen",
        "cover": "https://i.gr-assets.com/images/S/compressed.photo.goodreads.com/books/1499708658l/31450584._SX50_.jpg"
    },
    {
        "title": "The Horse, the Wheel, and Language: How Bronze-Age Riders from the Eurasian Steppes Shaped the Modern World",
        "author": "Anthony, David W.",
        "cover": "https://i.gr-assets.com/images/S/compressed.photo.goodreads.com/books/1619046003l/1831667._SY75_.jpg"
    },
    {
        "title": "The Unimaginable Mathematics of Borges' Library of Babel",
        "author": "Bloch, William Goldbloom",
        "cover": "https://i.gr-assets.com/images/S/compressed.photo.goodreads.com/books/1348216549l/2066384._SX50_.jpg"
    },
    {
        "title": "The Rise and Fall of the Dinosaurs: A New History of a Lost World",
        "author": "Brusatte, Steve",
        "cover": "https://i.gr-assets.com/images/S/compressed.photo.goodreads.com/books/1515529573l/35820369._SY75_.jpg"
    },
    {
        "title": "A Study of History, Abridgement of Vols 1-6",
        "author": "Toynbee, Arnold Joseph",
        "cover": "https://i.gr-assets.com/images/S/compressed.photo.goodreads.com/books/1359384051l/767233._SY75_.jpg"
    },
    {
        "title": "Too Much to Know: Managing Scholarly Information before the Modern Age",
        "author": "Blair, Ann M.",
        "cover": "https://i.gr-assets.com/images/S/compressed.photo.goodreads.com/books/1400951128l/8436175._SY75_.jpg"
    },
    {
        "title": "Napoleon: A Life",
        "author": "Roberts, Andrew",
        "cover": "https://i.gr-assets.com/images/S/compressed.photo.goodreads.com/books/1396671960l/20821092._SY75_.jpg"
    },
    {
        "title": "A Man on the Moon",
        "author": "Chaikin, Andrew",
        "cover": "https://i.gr-assets.com/images/S/compressed.photo.goodreads.com/books/1463586937l/896458._SY75_.jpg"
    },
    {
        "title": "American Revolutions: A Continental History, 1750-1804",
        "author": "Taylor, Alan",
        "cover": "https://i.gr-assets.com/images/S/compressed.photo.goodreads.com/books/1455299654l/28757817._SY75_.jpg"
    },
    {
        "title": "After the Ice: A Global Human History, 20,000-5000 BC",
        "author": "Mithen, Steven",
        "cover": "https://i.gr-assets.com/images/S/compressed.photo.goodreads.com/books/1388450150l/264288._SY75_.jpg"
    },
    {
        "title": "Late Migrations: A Natural History of Love and Loss",
        "author": "Renkl, Margaret",
        "cover": "https://i.gr-assets.com/images/S/compressed.photo.goodreads.com/books/1558972731l/42372550._SY75_.jpg"
    },
    {
        "title": "Our Oriental Heritage (The Story of Civilization, #1)",
        "author": "Durant, Will",
        "cover": "https://i.gr-assets.com/images/S/compressed.photo.goodreads.com/books/1652282857l/174722._SX50_.jpg"
    },
    {
        "title": "1491: New Revelations of the Americas Before Columbus",
        "author": "Mann, Charles C.",
        "cover": "https://i.gr-assets.com/images/S/compressed.photo.goodreads.com/books/1545238592l/39020._SY75_.jpg"
    },
    {
        "title": "The Napoleonic Wars (Smithsonian History of Warfare)",
        "author": "Rothenberg, Gunther E.",
        "cover": "https://i.gr-assets.com/images/S/compressed.photo.goodreads.com/books/1386925369l/234770._SY75_.jpg"
    },
    {
        "title": "Reputation and Power: Organizational Image and Pharmaceutical Regulation at the FDA (Princeton Studies in American Politics: Historical, International, and Comparative Perspectives, 111)",
        "author": "Carpenter, Daniel P.",
        "cover": "https://i.gr-assets.com/images/S/compressed.photo.goodreads.com/books/1347618413l/9176183._SY75_.jpg"
    },
    {
        "title": "The French Historical Revolution: The Annales School, 1929-1989 (Key Contemporary Thinkers)",
        "author": "Burke, Peter",
        "cover": "https://i.gr-assets.com/images/S/compressed.photo.goodreads.com/books/1407812796l/597060._SY75_.jpg"
    },
    {
        "title": "The Ancient City: A Study of the Religion, Laws, and Institutions of Greece and Rome (Dover Books on History, Political and Social Science)",
        "author": "Fustel de Coulanges, Numa Denis",
        "cover": "https://i.gr-assets.com/images/S/compressed.photo.goodreads.com/books/1328863636l/1260022._SY75_.jpg"
    },
    {
        "title": "Lee Kuan Yew: The Grand Master's Insights on China, the United States, and the World (Belfer Center Studies in International Security)",
        "author": "Allison, Graham",
        "cover": "https://i.gr-assets.com/images/S/compressed.photo.goodreads.com/books/1417983056l/16248652._SX50_.jpg"
    },
    {
        "title": "The Sources of Social Power: Volume 1, A History of Power from the Beginning to AD 1760",
        "author": "Mann, Michael",
        "cover": "https://i.gr-assets.com/images/S/compressed.photo.goodreads.com/books/1348871688l/397228._SX50_.jpg"
    },
    {
        "title": "The Coddling of the American Mind: How Good Intentions and Bad Ideas Are Setting Up a Generation for Failure",
        "author": "Haidt, Jonathan",
        "cover": "https://i.gr-assets.com/images/S/compressed.photo.goodreads.com/books/1513836885l/36556202._SY75_.jpg"
    },
    {
        "title": "Capitalist Realism: Is There No Alternative?",
        "author": "Fisher, Mark",
        "cover": "https://i.gr-assets.com/images/S/compressed.photo.goodreads.com/books/1426633608l/6763725._SY75_.jpg"
    },
    {
        "title": "Baseless: My Search for Secrets in the Ruins of the Freedom of Information Act",
        "author": "Baker, Nicholson",
        "cover": "https://i.gr-assets.com/images/S/compressed.photo.goodreads.com/books/1573869790l/48807215._SY75_.jpg"
    },
    {
        "title": "Letters to a Young Contrarian",
        "author": "Hitchens, Christopher",
        "cover": "https://i.gr-assets.com/images/S/compressed.photo.goodreads.com/books/1576449566l/503150._SY75_.jpg"
    },
    {
        "title": "Post-Rationalism: Psychoanalysis, Epistemology, and Marxism in Post-War France (Bloomsbury Studies in Continental Philosophy)",
        "author": "Eyers, Tom",
        "cover": "https://i.gr-assets.com/images/S/compressed.photo.goodreads.com/books/1379785246l/17188204._SY75_.jpg"
    },
    {
        "title": "Secrets of the Temple: How the Federal Reserve Runs the Country",
        "author": "Greider, William",
        "cover": "https://i.gr-assets.com/images/S/compressed.photo.goodreads.com/books/1348366617l/326358._SY75_.jpg"
    },
    {
        "title": "More Money Than God: Hedge Funds and the Making of a New Elite",
        "author": "Mallaby, Sebastian",
        "cover": "https://i.gr-assets.com/images/S/compressed.photo.goodreads.com/books/1432927841l/7936425._SY75_.jpg"
    },
    {
        "title": "Empire of Pain: The Secret History of the Sackler Dynasty",
        "author": "Keefe, Patrick Radden",
        "cover": "https://i.gr-assets.com/images/S/compressed.photo.goodreads.com/books/1611952534l/43868109._SY75_.jpg"
    },
    {
        "title": "Central Banking 101",
        "author": "Wang, Joseph J",
        "cover": "https://i.gr-assets.com/images/S/compressed.photo.goodreads.com/books/1611796718l/56863052._SY75_.jpg"
    },
    {
        "title": "The Great Crash of 1929",
        "author": "Galbraith, John Kenneth",
        "cover": "https://i.gr-assets.com/images/S/compressed.photo.goodreads.com/books/1592892631l/54234724._SY75_.jpg"
    },
    {
        "title": "The World for Sale: Money, Power and the Traders Who Barter the Earth’s Resources",
        "author": "Blas, Javier",
        "cover": "https://i.gr-assets.com/images/S/compressed.photo.goodreads.com/books/1616664353l/52199304._SY75_.jpg"
    },
    {
        "title": "The Big Four: The Curious Past and Perilous Future of the Global Accounting Monopoly",
        "author": "Gow, Ian D.",
        "cover": "https://i.gr-assets.com/images/S/compressed.photo.goodreads.com/books/1527078998l/36986347._SY75_.jpg"
    },
    {
        "title": "The Man Who Solved the Market: How Jim Simons Launched the Quant Revolution",
        "author": "Zuckerman, Gregory",
        "cover": "https://i.gr-assets.com/images/S/compressed.photo.goodreads.com/books/1567623099l/43889703._SY75_.jpg"
    },
    {
        "title": "The Greatest Trade Ever: The Behind-the-Scenes Story of How John Paulson Defied Wall Street and Made Financial History",
        "author": "Zuckerman, Gregory",
        "cover": "https://i.gr-assets.com/images/S/compressed.photo.goodreads.com/books/1320488806l/6986632._SY75_.jpg"
    },
    {
        "title": "21st Century Monetary Policy: The Federal Reserve from the Great Inflation to COVID-19",
        "author": "Bernanke, Ben S.",
        "cover": "https://i.gr-assets.com/images/S/compressed.photo.goodreads.com/books/1645247473l/58999217._SY75_.jpg"
    },
    {
        "title": "Why Nations Fail: The Origins of Power, Prosperity, and Poverty",
        "author": "Acemoğlu, Daron",
        "cover": "https://i.gr-assets.com/images/S/compressed.photo.goodreads.com/books/1348987396l/12158480._SY75_.jpg"
    },
    {
        "title": "The Ayatollah Begs to Differ: The Paradox of Modern Iran",
        "author": "Majd, Hooman",
        "cover": "https://i.gr-assets.com/images/S/compressed.photo.goodreads.com/books/1320445755l/3488337._SY75_.jpg"
    },
    {
        "title": "Mythos: The Greek Myths Retold (Stephen Fry's Great Mythology, #1)",
        "author": "Fry, Stephen",
        "cover": "https://i.gr-assets.com/images/S/compressed.photo.goodreads.com/books/1502518360l/35074096._SY75_.jpg"
    },
    {
        "title": "Mythology: Timeless Tales of Gods and Heroes",
        "author": "Hamilton, Edith",
        "cover": "https://i.gr-assets.com/images/S/compressed.photo.goodreads.com/books/1344265413l/8889013._SY75_.jpg"
    },
    {
        "title": "One Thousand and One Nights",
        "author": "Al-Shaykh, Hanan",
        "cover": "https://i.gr-assets.com/images/S/compressed.photo.goodreads.com/books/1363624580l/13109354._SX50_.jpg"
    },
    {
        "title": "The Arabian Nights",
        "author": "Anonymous",
        "cover": "https://i.gr-assets.com/images/S/compressed.photo.goodreads.com/books/1657544409l/93101._SY75_.jpg"
    },
    {
        "title": "The Dream Machine: J.C.R. Licklider and the Revolution That Made Computing Personal",
        "author": "Waldrop, M. Mitchell",
        "cover": "https://i.gr-assets.com/images/S/compressed.photo.goodreads.com/books/1309212000l/722412._SX50_.jpg"
    },
    {
        "title": "The Essential Turing: Seminal Writings in Computing, Logic, Philosophy, Artificial Intelligence, and Artificial Life plus The Secrets of Enigma",
        "author": "Turing, Alan",
        "cover": "https://i.gr-assets.com/images/S/compressed.photo.goodreads.com/books/1347421818l/150734._SX50_.jpg"
    },
    {
        "title": "The High Frontier: Human Colonies in Space (Apogee Books Space)",
        "author": "O'Neill, Gerard K.",
        "cover": "https://i.gr-assets.com/images/S/compressed.photo.goodreads.com/books/1347768443l/405001._SX50_.jpg"
    },
    {
        "title": "The Fourth Dimension: A Guided Tour of the Higher Universes",
        "author": "Rucker, Rudy",
        "cover": "https://i.gr-assets.com/images/S/compressed.photo.goodreads.com/books/1392182471l/274064._SX50_.jpg"
    },
    {
        "title": "Tao Te Ching",
        "author": "Lao Tzu",
        "cover": "https://i.gr-assets.com/images/S/compressed.photo.goodreads.com/books/1333578861l/67896._SY75_.jpg"
    },
    {
        "title": "On Writing Well: The Classic Guide to Writing Nonfiction",
        "author": "Zinsser, William",
        "cover": "https://i.gr-assets.com/images/S/compressed.photo.goodreads.com/books/1538764251l/53343._SY75_.jpg"
    },
    {
        "title": "A Swim in a Pond in the Rain: In Which Four Russians Give a Master Class on Writing, Reading, and Life",
        "author": "Saunders, George",
        "cover": "https://i.gr-assets.com/images/S/compressed.photo.goodreads.com/books/1627489209l/53487237._SY75_.jpg"
    },
    {
        "title": "The Name of the Rose",
        "author": "Eco, Umberto",
        "cover": "https://i.gr-assets.com/images/S/compressed.photo.goodreads.com/books/1415375471l/119073._SY75_.jpg"
    },
    {
        "title": "Slow Learner",
        "author": "Pynchon, Thomas",
        "cover": "https://i.gr-assets.com/images/S/compressed.photo.goodreads.com/books/1330433001l/5814._SY75_.jpg"
    },
    {
        "title": "Slaughterhouse-Five",
        "author": "Vonnegut, Kurt, Jr.",
        "cover": "https://i.gr-assets.com/images/S/compressed.photo.goodreads.com/books/1440319389l/4981._SY75_.jpg"
    },
    {
        "title": "Waiting for Godot",
        "author": "Beckett, Samuel",
        "cover": "https://i.gr-assets.com/images/S/compressed.photo.goodreads.com/books/1327910301l/17716._SY75_.jpg"
    },
    {
        "title": "Neuromancer (Sprawl, #1)",
        "author": "Gibson, William",
        "cover": "https://i.gr-assets.com/images/S/compressed.photo.goodreads.com/books/1554437249l/6088007._SY75_.jpg"
    },
    {
        "title": "The Graveyard Book",
        "author": "Gaiman, Neil",
        "cover": "https://i.gr-assets.com/images/S/compressed.photo.goodreads.com/books/1531295292l/2213661._SY75_.jpg"
    },
    {
        "title": "House of Leaves",
        "author": "Danielewski, Mark Z.",
        "cover": "https://i.gr-assets.com/images/S/compressed.photo.goodreads.com/books/1403889034l/24800._SX50_.jpg"
    },
    {
        "title": "Stoner",
        "author": "Williams, John",
        "cover": "https://i.gr-assets.com/images/S/compressed.photo.goodreads.com/books/1320600716l/166997._SY75_.jpg"
    },
    {
        "title": "Tinker, Tailor, Soldier, Spy (George Smiley, #5; Karla Trilogy, #1)",
        "author": "le Carré, John",
        "cover": "https://i.gr-assets.com/images/S/compressed.photo.goodreads.com/books/1349070201l/10073506._SX50_.jpg"
    },
    {
        "title": "The French Lieutenant’s Woman",
        "author": "Fowles, John",
        "cover": "https://i.gr-assets.com/images/S/compressed.photo.goodreads.com/books/1466630905l/56034._SY75_.jpg"
    },
    {
        "title": "On the Road",
        "author": "Kerouac, Jack",
        "cover": "https://i.gr-assets.com/images/S/compressed.photo.goodreads.com/books/1658929891l/70401._SY75_.jpg"
    },
    {
        "title": "Invisible Cities",
        "author": "Calvino, Italo",
        "cover": "https://i.gr-assets.com/images/S/compressed.photo.goodreads.com/books/1468623303l/9809._SY75_.jpg"
    },
    {
        "title": "In Search of Lost Time",
        "author": "Proust, Marcel",
        "cover": "https://i.gr-assets.com/images/S/compressed.photo.goodreads.com/books/1657567516l/18796._SX50_.jpg"
    },
    {
        "title": "Steppenwolf",
        "author": "Hesse, Hermann",
        "cover": "https://i.gr-assets.com/images/S/compressed.photo.goodreads.com/books/1389332672l/16631._SY75_.jpg"
    },
    {
        "title": "What I Talk About When I Talk About Running",
        "author": "Murakami, Haruki",
        "cover": "https://i.gr-assets.com/images/S/compressed.photo.goodreads.com/books/1473397159l/2195464._SY75_.jpg"
    },
    {
        "title": "I Have No Mouth & I Must Scream",
        "author": "Ellison, Harlan",
        "cover": "https://i.gr-assets.com/images/S/compressed.photo.goodreads.com/books/1423672898l/415459._SY75_.jpg"
    },
    {
        "title": "Gravity’s Rainbow",
        "author": "Pynchon, Thomas",
        "cover": "https://i.gr-assets.com/images/S/compressed.photo.goodreads.com/books/1657594227l/415._SY75_.jpg"
    },
    {
        "title": "Lord of the Flies",
        "author": "Golding, William",
        "cover": "https://i.gr-assets.com/images/S/compressed.photo.goodreads.com/books/1327869409l/7624._SY75_.jpg"
    },
    {
        "title": "The New Atlantis",
        "author": "Bacon, Francis",
        "cover": "https://i.gr-assets.com/images/S/compressed.photo.goodreads.com/books/1348118743l/277032._SX50_.jpg"
    },
    {
        "title": "The Book of Disquiet",
        "author": "Pessoa, Fernando",
        "cover": "https://i.gr-assets.com/images/S/compressed.photo.goodreads.com/books/1631144816l/45974._SY75_.jpg"
    },
    {
        "title": "Far From the Madding Crowd",
        "author": "Hardy, Thomas",
        "cover": "https://i.gr-assets.com/images/S/compressed.photo.goodreads.com/books/1631259654l/31463._SY75_.jpg"
    },
    {
        "title": "The Denial of Death",
        "author": "Becker, Ernest",
        "cover": "https://i.gr-assets.com/images/S/compressed.photo.goodreads.com/books/1388432490l/2761._SY75_.jpg"
    },
    {
        "title": "Death in Venice",
        "author": "Mann, Thomas",
        "cover": "https://i.gr-assets.com/images/S/compressed.photo.goodreads.com/books/1627232919l/53061._SY75_.jpg"
    },
    {
        "title": "White Noise",
        "author": "DeLillo, Don",
        "cover": "https://i.gr-assets.com/images/S/compressed.photo.goodreads.com/books/1476807953l/28251250._SY75_.jpg"
    },
    {
        "title": "The Postman",
        "author": "Brin, David",
        "cover": "https://i.gr-assets.com/images/S/compressed.photo.goodreads.com/books/1614051119l/889284._SY75_.jpg"
    },
    {
        "title": "The Unincorporated Man  (Unincorporated Man, #1)",
        "author": "Kollin, Dani",
        "cover": "https://i.gr-assets.com/images/S/compressed.photo.goodreads.com/books/1312055153l/4025200._SY75_.jpg"
    },
    {
        "title": "Crime and Punishment",
        "author": "Dostoevsky, Fyodor",
        "cover": "https://i.gr-assets.com/images/S/compressed.photo.goodreads.com/books/1382846449l/7144._SY75_.jpg"
    },
    {
        "title": "Fight Club",
        "author": "Palahniuk, Chuck",
        "cover": "https://i.gr-assets.com/images/S/compressed.photo.goodreads.com/books/1558216416l/36236124._SY75_.jpg"
    },
    {
        "title": "Consider This: Moments in My Writing Life After Which Everything Was Different",
        "author": "Palahniuk, Chuck",
        "cover": "https://i.gr-assets.com/images/S/compressed.photo.goodreads.com/books/1568319190l/52500766._SX50_SY75_.jpg"
    },
    {
        "title": "Things Fall Apart (The African Trilogy, #1)",
        "author": "Achebe, Chinua",
        "cover": "https://i.gr-assets.com/images/S/compressed.photo.goodreads.com/books/1708114013l/37781._SY75_.jpg"
    },
    {
        "title": "Cat’s Cradle",
        "author": "Vonnegut, Kurt, Jr.",
        "cover": "https://i.gr-assets.com/images/S/compressed.photo.goodreads.com/books/1327867150l/135479._SY75_.jpg"
    },
    {
        "title": "The Abolition of Man",
        "author": "Lewis, C.S.",
        "cover": "https://i.gr-assets.com/images/S/compressed.photo.goodreads.com/books/1435685201l/25825420._SY75_.jpg"
    },
    {
        "title": "Burning Chrome (Sprawl, #0)",
        "author": "Gibson, William",
        "cover": "https://i.gr-assets.com/images/S/compressed.photo.goodreads.com/books/1349075772l/22323._SY75_.jpg"
    },
    {
        "title": "The Fountainhead",
        "author": "Rand, Ayn",
        "cover": "https://i.gr-assets.com/images/S/compressed.photo.goodreads.com/books/1491163636l/2122._SY75_.jpg"
    },
    {
        "title": "Atlas Shrugged",
        "author": "Rand, Ayn",
        "cover": "https://i.gr-assets.com/images/S/compressed.photo.goodreads.com/books/1405868167l/662._SY75_.jpg"
    },
    {
        "title": "All Things are Possible (Apotheosis of Groundlessness)",
        "author": "Lev, Shestov",
        "cover": "https://i.gr-assets.com/images/S/compressed.photo.goodreads.com/books/1355133563l/7030725._SY75_.jpg"
    },
    {
        "title": "In the First Circle",
        "author": "Solzhenitsyn, Aleksandr",
        "cover": "https://i.gr-assets.com/images/S/compressed.photo.goodreads.com/books/1635713188l/2080190._SY75_.jpg"
    },
    {
        "title": "A Man Without a Country",
        "author": "Vonnegut, Kurt, Jr.",
        "cover": "https://i.gr-assets.com/images/S/compressed.photo.goodreads.com/books/1330997432l/4979._SY75_.jpg"
    },
    {
        "title": "A Canticle for Leibowitz (St. Leibowitz, #1)",
        "author": "Miller Jr., Walter M.",
        "cover": "https://i.gr-assets.com/images/S/compressed.photo.goodreads.com/books/1450516880l/164154._SY75_.jpg"
    },
    {
        "title": "A Bull of a Man: Images of Masculinity, Sex, and the Body in Indian Buddhism",
        "author": "Powers, John",
        "cover": "https://i.gr-assets.com/images/S/compressed.photo.goodreads.com/books/1347943678l/6929420._SY75_.jpg"
    },
    {
        "title": "The Crying of Lot 49",
        "author": "Pynchon, Thomas",
        "cover": "https://i.gr-assets.com/images/S/compressed.photo.goodreads.com/books/1657594162l/2794._SY75_.jpg"
    },
    {
        "title": "The Outsider",
        "author": "Camus, Albert",
        "cover": "https://i.gr-assets.com/images/S/compressed.photo.goodreads.com/books/1435772042l/15686._SY75_.jpg"
    },
    {
        "title": "The Aeneid",
        "author": "Virgil",
        "cover": "https://i.gr-assets.com/images/S/compressed.photo.goodreads.com/books/1386923968l/12914._SY75_.jpg"
    },
    {
        "title": "The Picture of Dorian Gray",
        "author": "Wilde, Oscar",
        "cover": "https://i.gr-assets.com/images/S/compressed.photo.goodreads.com/books/1546103428l/5297._SY75_.jpg"
    },
    {
        "title": "The Trial",
        "author": "Kafka, Franz",
        "cover": "https://i.gr-assets.com/images/S/compressed.photo.goodreads.com/books/1320399438l/17690._SY75_.jpg"
    },
    {
        "title": "The Road to Serfdom",
        "author": "Hayek, Friedrich",
        "cover": "https://i.gr-assets.com/images/S/compressed.photo.goodreads.com/books/1327787673l/299215._SY75_.jpg"
    },
    {
        "title": "The House of the Dead",
        "author": "Dostoevsky, Fyodor",
        "cover": "https://i.gr-assets.com/images/S/compressed.photo.goodreads.com/books/1327908745l/17877._SY75_.jpg"
    },
    {
        "title": "The Adventures of Huckleberry Finn",
        "author": "Twain, Mark",
        "cover": "https://i.gr-assets.com/images/S/compressed.photo.goodreads.com/books/1546096879l/2956._SX50_.jpg"
    },
    {
        "title": "Coyote America: A Natural and Supernatural History",
        "author": "Flores, Dan",
        "cover": "https://i.gr-assets.com/images/S/compressed.photo.goodreads.com/books/1448320143l/26195972._SY75_.jpg"
    },
    {
        "title": "Being Different: An Indian Challenge to Western Universalism",
        "author": "Malhotra, Rajiv",
        "cover": "https://i.gr-assets.com/images/S/compressed.photo.goodreads.com/books/1340783111l/13099825._SX50_.jpg"
    },
    {
        "title": "The Mind Illuminated: A Complete Meditation Guide Integrating Buddhist Wisdom and Brain Science",
        "author": "Yates), Culadasa (John Charles",
        "cover": "https://i.gr-assets.com/images/S/compressed.photo.goodreads.com/books/1439857546l/25942786._SX50_.jpg"
    },
    {
        "title": "The Body Keeps the Score: Brain, Mind, and Body in the Healing of Trauma",
        "author": "Kolk, Bessel van der",
        "cover": "https://i.gr-assets.com/images/S/compressed.photo.goodreads.com/books/1594559067l/18693771._SY75_.jpg"
    },
    {
        "title": "I Will Teach You to Be Rich: No Guilt. No Excuses. No BS. Just a 6-Week Program That Works",
        "author": "Sethi, Ramit",
        "cover": "https://i.gr-assets.com/images/S/compressed.photo.goodreads.com/books/1552228430l/40591670._SY75_.jpg"
    },
    {
        "title": "What I Learned About Investing from Darwin",
        "author": "Prasad, Pulak",
        "cover": "https://i.gr-assets.com/images/S/compressed.photo.goodreads.com/books/1672014345l/62792694._SY75_.jpg"
    },
    {
        "title": "The Origin of Wealth: Evolution, Complexity, and the Radical Remaking of Economics",
        "author": "Beinhocker, Eric D.",
        "cover": "https://i.gr-assets.com/images/S/compressed.photo.goodreads.com/books/1388330469l/22456._SX50_.jpg"
    },
    {
        "title": "Debt: The First 5,000 Years",
        "author": "Graeber, David",
        "cover": "https://i.gr-assets.com/images/S/compressed.photo.goodreads.com/books/1390408633l/6617037._SY75_.jpg"
    },
    {
        "title": "Start-up Nation: The Story of Israel's Economic Miracle",
        "author": "Senor, Dan",
        "cover": "https://i.gr-assets.com/images/S/compressed.photo.goodreads.com/books/1344269860l/6885191._SY75_.jpg"
    },
    {
        "title": "Coined: The Rich Life of Money and How Its History Has Shaped Us",
        "author": "Sehgal, Kabir",
        "cover": "https://i.gr-assets.com/images/S/compressed.photo.goodreads.com/books/1418767358l/23435145._SY75_.jpg"
    },
    {
        "title": "The Lords of Easy Money: How the Federal Reserve Broke the American Economy",
        "author": "Leonard, Christopher",
        "cover": "https://i.gr-assets.com/images/S/compressed.photo.goodreads.com/books/1636903374l/58485511._SX50_.jpg"
    },
    {
        "title": "Engines That Move Markets: Technology Investing from Railroads to the Internet and Beyond",
        "author": "Nairn, Alasdair",
        "cover": "https://i.gr-assets.com/images/S/compressed.photo.goodreads.com/books/1356455376l/1458370._SY75_.jpg"
    },
    {
        "title": "Ogilvy on Advertising",
        "author": "Ogilvy, David",
        "cover": "https://i.gr-assets.com/images/S/compressed.photo.goodreads.com/books/1320545976l/641601._SX50_.jpg"
    },
    {
        "title": "The Hard Thing About Hard Things: Building a Business When There Are No Easy Answers",
        "author": "Horowitz, Ben",
        "cover": "https://i.gr-assets.com/images/S/compressed.photo.goodreads.com/books/1386609333l/18176747._SY75_.jpg"
    },
    {
        "title": "Invent and Wander: The Collected Writings of Jeff Bezos",
        "author": "Bezos, Jeff",
        "cover": "https://i.gr-assets.com/images/S/compressed.photo.goodreads.com/books/1600744841l/54505323._SY75_.jpg"
    },
    {
        "title": "The Lives of a Cell: Notes of a Biology Watcher",
        "author": "Thomas, Lewis",
        "cover": "https://i.gr-assets.com/images/S/compressed.photo.goodreads.com/books/1348684638l/294368._SY75_.jpg"
    },
    {
        "title": "Neuroplasticity (The MIT Press Essential Knowledge series)",
        "author": "Costandi, Moheb",
        "cover": "https://i.gr-assets.com/images/S/compressed.photo.goodreads.com/books/1562990666l/29889529._SX50_.jpg"
    },
    {
        "title": "Entangled Life: How Fungi Make Our Worlds, Change Our Minds & Shape Our Futures",
        "author": "Sheldrake, Merlin",
        "cover": "https://i.gr-assets.com/images/S/compressed.photo.goodreads.com/books/1575341220l/52668915._SX50_SY75_.jpg"
    },
    {
        "title": "An Outsider's Guide to Humans: What Science Taught Me About What We Do and Who We Are",
        "author": "Pang, Camilla",
        "cover": "https://i.gr-assets.com/images/S/compressed.photo.goodreads.com/books/1620326952l/52559342._SY75_.jpg"
    },
    {
        "title": "The Doors of Perception",
        "author": "Huxley, Aldous",
        "cover": "https://i.gr-assets.com/images/S/compressed.photo.goodreads.com/books/1364525216l/3188964._SX50_.jpg"
    },
    {
        "title": "Hagakure: The Book of the Samurai",
        "author": "Yamamoto Tsunetomo",
        "cover": "https://i.gr-assets.com/images/S/compressed.photo.goodreads.com/books/1388186715l/277950._SX50_.jpg"
    },
    {
        "title": "Genghis Khan and the Making of the Modern World",
        "author": "Weatherford, Jack",
        "cover": "https://i.gr-assets.com/images/S/compressed.photo.goodreads.com/books/1530716694l/40718726._SY75_.jpg"
    },
    {
        "title": "Food of the Gods: The Search for the Original Tree of Knowledge",
        "author": "McKenna, Terence",
        "cover": "https://i.gr-assets.com/images/S/compressed.photo.goodreads.com/books/1388178573l/51660._SY75_.jpg"
    },
    {
        "title": "Masters of Doom: How Two Guys Created an Empire and Transformed Pop Culture",
        "author": "Kushner, David",
        "cover": "https://i.gr-assets.com/images/S/compressed.photo.goodreads.com/books/1557932856l/222146._SY75_.jpg"
    },
    {
        "title": "Poor Charlie's Almanack: The Wit and Wisdom of Charles T. Munger",
        "author": "Munger, Charles T.",
        "cover": "https://i.gr-assets.com/images/S/compressed.photo.goodreads.com/books/1387744370l/944652._SX50_.jpg"
    },
    {
        "title": "Good Profit: How Creating Value for Others Built One of the World's Most Successful Companies",
        "author": "Koch, Charles G.",
        "cover": "https://i.gr-assets.com/images/S/compressed.photo.goodreads.com/books/1444622832l/25058203._SX50_.jpg"
    },
    {
        "title": "Bad Blood: Secrets and Lies in a Silicon Valley Startup",
        "author": "Carreyrou, John",
        "cover": "https://i.gr-assets.com/images/S/compressed.photo.goodreads.com/books/1523311515l/37976541._SX50_.jpg"
    },
    {
        "title": "Alexander the Great",
        "author": "Cartledge, Paul Anthony",
        "cover": "https://i.gr-assets.com/images/S/compressed.photo.goodreads.com/books/1320403560l/220608._SY75_.jpg"
    },
    {
        "title": "Alexander of Macedon, 356-323 B.C.",
        "author": "Green, Peter",
        "cover": "https://i.gr-assets.com/images/S/compressed.photo.goodreads.com/books/1388881134l/232124._SY75_.jpg"
    },
    {
        "title": "Caesar: Life of a Colossus",
        "author": "Goldsworthy, Adrian",
        "cover": "https://i.gr-assets.com/images/S/compressed.photo.goodreads.com/books/1386924302l/60432._SY75_.jpg"
    },
    {
        "title": "The extension of man: A history of physics before 1900",
        "author": "Bernal, J.D.",
        "cover": "https://s.gr-assets.com/assets/nophoto/book/50x75-a91bf249278a81aabab721ef782c4a74.png"
    },
    {
        "title": "Kelly: More Than My Share of It All",
        "author": "Johnson, Clarence L.",
        "cover": "https://i.gr-assets.com/images/S/compressed.photo.goodreads.com/books/1320401064l/1354758._SY75_.jpg"
    },
    {
        "title": "Plentiful Energy: The Story of the Integral Fast Reactor: The complex history of a simple reactor technology, with emphasis on its scientific bases for non-specialists",
        "author": "Till, Charles E.",
        "cover": "https://i.gr-assets.com/images/S/compressed.photo.goodreads.com/books/1393220827l/13393683._SX50_.jpg"
    },
    {
        "title": "The Principia : Mathematical Principles of Natural Philosophy",
        "author": "Newton, Isaac",
        "cover": "https://i.gr-assets.com/images/S/compressed.photo.goodreads.com/books/1386924124l/231083._SY75_.jpg"
    },
    {
        "title": "The Supermen: The Story of Seymour Cray and the Technical Wizards Behind the Supercomputer",
        "author": "Murray, Charles J.",
        "cover": "https://i.gr-assets.com/images/S/compressed.photo.goodreads.com/books/1348932939l/116196._SX50_.jpg"
    },
    {
        "title": "The Making of a Manager: What to Do When Everyone Looks to You",
        "author": "Zhuo, Julie",
        "cover": "https://i.gr-assets.com/images/S/compressed.photo.goodreads.com/books/1548809382l/38821039._SY75_.jpg"
    },
    {
        "title": "Pandaemonium: The Coming of the Machine As Seen by Contemporary Observers",
        "author": "Jennings, Humphrey",
        "cover": "https://i.gr-assets.com/images/S/compressed.photo.goodreads.com/books/1356136423l/2313641._SY75_.jpg"
    },
    {
        "title": "Endurance: Shackleton's Incredible Voyage",
        "author": "Lansing, Alfred",
        "cover": "https://i.gr-assets.com/images/S/compressed.photo.goodreads.com/books/1391329559l/139069._SY75_.jpg"
    },
    {
        "title": "The Old Way: A Story of the First People",
        "author": "Thomas, Elizabeth Marshall",
        "cover": "https://i.gr-assets.com/images/S/compressed.photo.goodreads.com/books/1312005141l/544855._SY75_.jpg"
    },
    {
        "title": "The Origin of Consciousness in the Breakdown of the Bicameral Mind",
        "author": "Jaynes, Julian",
        "cover": "https://i.gr-assets.com/images/S/compressed.photo.goodreads.com/books/1388305401l/22478._SY75_.jpg"
    },
    {
        "title": "Solution Selling: Creating Buyers in Difficult Selling Markets",
        "author": "Bosworth, Michael T.",
        "cover": "https://i.gr-assets.com/images/S/compressed.photo.goodreads.com/books/1347889528l/514592._SX50_.jpg"
    },
    {
        "title": "Winning",
        "author": "Welch, Jack",
        "cover": "https://i.gr-assets.com/images/S/compressed.photo.goodreads.com/books/1366775828l/866222._SY75_.jpg"
    },
    {
        "title": "The Beak of the Finch: A Story of Evolution in Our Time",
        "author": "Weiner, Jonathan",
        "cover": "https://i.gr-assets.com/images/S/compressed.photo.goodreads.com/books/1328236736l/125286._SY75_.jpg"
    },
    {
        "title": "Mathematician's Delight",
        "author": "Sawyer, W. W.",
        "cover": "https://i.gr-assets.com/images/S/compressed.photo.goodreads.com/books/1266726483l/1134117._SY75_.jpg"
    },
    {
        "title": "Creation: Life and How to Make It",
        "author": "Grand, Steve",
        "cover": "https://i.gr-assets.com/images/S/compressed.photo.goodreads.com/books/1347482369l/304444._SY75_.jpg"
    },
    {
        "title": "The Goal: A Process of Ongoing Improvement",
        "author": "Goldratt, Eliyahu M.",
        "cover": "https://i.gr-assets.com/images/S/compressed.photo.goodreads.com/books/1475538019l/113934._SX50_.jpg"
    },
    {
        "title": "The Long Weekend: Life in the English Country House Between the Wars",
        "author": "Tinniswood, Adrian",
        "cover": "https://i.gr-assets.com/images/S/compressed.photo.goodreads.com/books/1464674856l/24385886._SX50_.jpg"
    },
    {
        "title": "Idea Makers: Personal Perspectives on the Lives & Ideas of Some Notable People",
        "author": "Wolfram, Stephen",
        "cover": "https://i.gr-assets.com/images/S/compressed.photo.goodreads.com/books/1468669633l/30618260._SX50_.jpg"
    },
    {
        "title": "The French Revolution and What Went Wrong",
        "author": "Clarke, Stephen",
        "cover": "https://i.gr-assets.com/images/S/compressed.photo.goodreads.com/books/1525302254l/40026402._SY75_.jpg"
    },
    {
        "title": "The Harmless People",
        "author": "Thomas, Elizabeth Marshall",
        "cover": "https://i.gr-assets.com/images/S/compressed.photo.goodreads.com/books/1403171381l/544856._SY75_.jpg"
    },
    {
        "title": "The Tartar Steppe",
        "author": "Buzzati, Dino",
        "cover": "https://i.gr-assets.com/images/S/compressed.photo.goodreads.com/books/1327904364l/83017._SY75_.jpg"
    },
    {
        "title": "How Nature Works: The Science of Self-organized Criticality",
        "author": "Bak, Per",
        "cover": "https://i.gr-assets.com/images/S/compressed.photo.goodreads.com/books/1406510770l/869836._SY75_.jpg"
    },
    {
        "title": "Perilous Interventions: The Security Council and the Politics of Chaos",
        "author": "Puri, Hardeep Singh",
        "cover": "https://i.gr-assets.com/images/S/compressed.photo.goodreads.com/books/1473434592l/31448865._SY75_.jpg"
    },
    {
        "title": "The Structure of Scientific Revolutions",
        "author": "Kuhn, Thomas S.",
        "cover": "https://i.gr-assets.com/images/S/compressed.photo.goodreads.com/books/1396422530l/61539._SY75_.jpg"
    },
    {
        "title": "The Lunar Men: Five Friends Whose Curiosity Changed the World",
        "author": "Uglow, Jenny",
        "cover": "https://i.gr-assets.com/images/S/compressed.photo.goodreads.com/books/1439772717l/451211._SY75_.jpg"
    },
    {
        "title": "Just Six Numbers: The Deep Forces That Shape the Universe",
        "author": "Rees, Martin J.",
        "cover": "https://i.gr-assets.com/images/S/compressed.photo.goodreads.com/books/1272137984l/81884._SX50_.jpg"
    },
    {
        "title": "The Moral Landscape: How Science Can Determine Human Values",
        "author": "Harris, Sam",
        "cover": "https://i.gr-assets.com/images/S/compressed.photo.goodreads.com/books/1331317058l/7785194._SY75_.jpg"
    },
    {
        "title": "The Science of Can and Can't: A Physicist’s Journey Through the Land of Counterfactuals",
        "author": "Marletto, Chiara",
        "cover": "https://i.gr-assets.com/images/S/compressed.photo.goodreads.com/books/1616017771l/54837100._SY75_.jpg"
    },
    {
        "title": "Capital in the Twenty First Century",
        "author": "Piketty, Thomas",
        "cover": "https://i.gr-assets.com/images/S/compressed.photo.goodreads.com/books/1390111547l/18736925._SY75_.jpg"
    },
    {
        "title": "Discourses on Livy",
        "author": "Machiavelli, Niccolò",
        "cover": "https://i.gr-assets.com/images/S/compressed.photo.goodreads.com/books/1328873823l/167924._SY75_.jpg"
    },
    {
        "title": "The City and the Stars",
        "author": "Clarke, Arthur C.",
        "cover": "https://i.gr-assets.com/images/S/compressed.photo.goodreads.com/books/1340242824l/250024._SY75_.jpg"
    },
    {
        "title": "Principia Discordia",
        "author": "Miller, Frederic P.",
        "cover": "https://i.gr-assets.com/images/S/compressed.photo.goodreads.com/books/1347579489l/10099655._SX50_.jpg"
    },
    {
        "title": "The Physics of Sorrow",
        "author": "Gospodinov, Georgi",
        "cover": "https://i.gr-assets.com/images/S/compressed.photo.goodreads.com/books/1415678093l/23129709._SY75_.jpg"
    },
    {
        "title": "Generation X: Tales for an Accelerated Culture",
        "author": "Coupland, Douglas",
        "cover": "https://i.gr-assets.com/images/S/compressed.photo.goodreads.com/books/1485623844l/3378._SY75_.jpg"
    },
    {
        "title": "S.",
        "author": "Abrams, J.J.",
        "cover": "https://i.gr-assets.com/images/S/compressed.photo.goodreads.com/books/1378767595l/17860739._SY75_.jpg"
    },
    {
        "title": "Story: Substance, Structure, Style, and the Principles of Screenwriting",
        "author": "McKee, Robert",
        "cover": "https://i.gr-assets.com/images/S/compressed.photo.goodreads.com/books/1388176882l/48654._SY75_.jpg"
    },
    {
        "title": "The Opposing Shore",
        "author": "Gracq, Julien",
        "cover": "https://i.gr-assets.com/images/S/compressed.photo.goodreads.com/books/1686902477l/2033025._SY75_.jpg"
    },
    {
        "title": "Dictionary of the Khazars",
        "author": "Pavić, Milorad",
        "cover": "https://i.gr-assets.com/images/S/compressed.photo.goodreads.com/books/1320461994l/321566._SY75_.jpg"
    },
    {
        "title": "Ulysses",
        "author": "Joyce, James",
        "cover": "https://i.gr-assets.com/images/S/compressed.photo.goodreads.com/books/1428891345l/338798._SY75_.jpg"
    },
    {
        "title": "If on a Winter’s Night a Traveler",
        "author": "Calvino, Italo",
        "cover": "https://i.gr-assets.com/images/S/compressed.photo.goodreads.com/books/1528312857l/374233._SY75_.jpg"
    },
    {
        "title": "Hopscotch",
        "author": "Cortázar, Julio",
        "cover": "https://i.gr-assets.com/images/S/compressed.photo.goodreads.com/books/1367728486l/53413._SY75_.jpg"
    },
    {
        "title": "Syllabus: Notes from an Accidental Professor",
        "author": "Barry, Lynda",
        "cover": "https://i.gr-assets.com/images/S/compressed.photo.goodreads.com/books/1393646674l/20613619._SX50_.jpg"
    },
    {
        "title": "Nox",
        "author": "Carson, Anne",
        "cover": "https://i.gr-assets.com/images/S/compressed.photo.goodreads.com/books/1348907960l/7428663._SY75_.jpg"
    },
    {
        "title": "Diableries: Stereoscopic Adventures in Hell",
        "author": "May, Brian",
        "cover": "https://i.gr-assets.com/images/S/compressed.photo.goodreads.com/books/1378102859l/18350992._SX50_.jpg"
    },
    {
        "title": "Probability Theory: The Logic of Science",
        "author": "Jaynes, E.T.",
        "cover": "https://i.gr-assets.com/images/S/compressed.photo.goodreads.com/books/1408310817l/151848._SX50_.jpg"
    },
    {
        "title": "The Adapted Mind: Evolutionary Psychology and the Generation of Culture",
        "author": "Barkow, Jerome H.",
        "cover": "https://i.gr-assets.com/images/S/compressed.photo.goodreads.com/books/1347470676l/1056451._SY75_.jpg"
    },
    {
        "title": "Rationality: From AI to Zombies",
        "author": "Yudkowsky, Eliezer",
        "cover": "https://i.gr-assets.com/images/S/compressed.photo.goodreads.com/books/1440562023l/25131230._SX50_.jpg"
    },
    {
        "title": "Inadequate Equilibria: Where and How Civilizations Get Stuck",
        "author": "Yudkowsky, Eliezer",
        "cover": "https://i.gr-assets.com/images/S/compressed.photo.goodreads.com/books/1510848448l/36606376._SY75_.jpg"
    },
    {
        "title": "Superforecasting: The Art and Science of Prediction",
        "author": "Tetlock, Philip E.",
        "cover": "https://i.gr-assets.com/images/S/compressed.photo.goodreads.com/books/1435684424l/23995360._SY75_.jpg"
    },
    {
        "title": "Intuition Pumps And Other Tools for Thinking",
        "author": "Dennett, Daniel C.",
        "cover": "https://i.gr-assets.com/images/S/compressed.photo.goodreads.com/books/1381288490l/18378002._SX50_.jpg"
    },
    {
        "title": "The Prince",
        "author": "Machiavelli, Niccolò",
        "cover": "https://i.gr-assets.com/images/S/compressed.photo.goodreads.com/books/1390055828l/28862._SY75_.jpg"
    },
    {
        "title": "Manufacturing Consent: The Political Economy of the Mass Media",
        "author": "Herman, Edward S.",
        "cover": "https://i.gr-assets.com/images/S/compressed.photo.goodreads.com/books/1525166345l/12617._SY75_.jpg"
    },
    {
        "title": "Menti tribali: Perché le brave persone di dividono su politica e religione",
        "author": "Haidt, Jonathan",
        "cover": "https://i.gr-assets.com/images/S/compressed.photo.goodreads.com/books/1680445605l/124939807._SY75_.jpg"
    },
    {
        "title": "The Organization Man",
        "author": "Whyte, William H.",
        "cover": "https://i.gr-assets.com/images/S/compressed.photo.goodreads.com/books/1388713607l/725027._SY75_.jpg"
    },
    {
        "title": "High Output Management",
        "author": "Grove, Andrew S.",
        "cover": "https://i.gr-assets.com/images/S/compressed.photo.goodreads.com/books/1347800461l/324750._SY75_.jpg"
    },
    {
        "title": "Red Notice: A True Story of High Finance, Murder, and One Man's Fight for Justice",
        "author": "Browder, Bill",
        "cover": "https://i.gr-assets.com/images/S/compressed.photo.goodreads.com/books/1422848658l/22609522._SY75_.jpg"
    },
    {
        "title": "Dealers of Lightning: Xerox PARC and the Dawn of the Computer Age",
        "author": "Hiltzik, Michael A.",
        "cover": "https://i.gr-assets.com/images/S/compressed.photo.goodreads.com/books/1349086333l/1101290._SX50_.jpg"
    },
    {
        "title": "A Pattern Language: Towns, Buildings, Construction (Center for Environmental Structure Series)",
        "author": "Alexander, Christopher W.",
        "cover": "https://i.gr-assets.com/images/S/compressed.photo.goodreads.com/books/1437097809l/79766._SY75_.jpg"
    }
]