[{"title": "Grendel", "author": "Gardner, John", "cover": "https://i.gr-assets.com/images/S/compressed.photo.goodreads.com/books/1347871284l/676737._SY75_.jpg"}, {"title": "The Inner Game of Tennis: The Classic Guide to the Mental Side of Peak Performance", "author": "Gallwey, W. Timothy", "cover": "https://i.gr-assets.com/images/S/compressed.photo.goodreads.com/books/1427665815l/905._SY75_.jpg"}, {"title": "Against Method", "author": "Feyerabend, Paul Karl", "cover": "https://i.gr-assets.com/images/S/compressed.photo.goodreads.com/books/1373999202l/137979._SY75_.jpg"}, {"title": "Germinal", "author": "Zola, \u00c9mile", "cover": "https://i.gr-assets.com/images/S/compressed.photo.goodreads.com/books/1628462562l/28407._SY75_.jpg"}, {"title": "Ficciones", "author": "Borges, Jorge Luis", "cover": "https://i.gr-assets.com/images/S/compressed.photo.goodreads.com/books/1621713120l/426504._SY75_.jpg"}, {"title": "The Melancholy of Resistance", "author": "Krasznahorkai, L\u00e1szl\u00f3", "cover": "https://i.gr-assets.com/images/S/compressed.photo.goodreads.com/books/1656784717l/119512._SY75_.jpg"}, {"title": "Philosophy and Simulation: The Emergence of Synthetic Reason", "author": "DeLanda, Manuel", "cover": "https://i.gr-assets.com/images/S/compressed.photo.goodreads.com/books/1347311133l/10393464._SY75_.jpg"}, {"title": "Good Thinking: The Foundations of Probability and Its Applications (Dover Books on Mathematics)", "author": "Good, Irving John", "cover": "https://i.gr-assets.com/images/S/compressed.photo.goodreads.com/books/1328863167l/6638587._SY75_.jpg"}, {"title": "The Diving Bell and the Butterfly", "author": "Bauby, Jean-Dominique", "cover": "https://i.gr-assets.com/images/S/compressed.photo.goodreads.com/books/1336930564l/193755._SY75_.jpg"}, {"title": "Contagious: Why Things Catch On", "author": "Berger, Jonah", "cover": "https://i.gr-assets.com/images/S/compressed.photo.goodreads.com/books/1376783352l/15801967._SY75_.jpg"}, {"title": "The Emotional Brain: The Mysterious Underpinnings of Emotional Life", "author": "LeDoux, Joseph E.", "cover": "https://i.gr-assets.com/images/S/compressed.photo.goodreads.com/books/1348557712l/780672._SY75_.jpg"}, {"title": "Thinking In Systems: A Primer", "author": "Meadows, Donella H.", "cover": "https://i.gr-assets.com/images/S/compressed.photo.goodreads.com/books/1390169859l/3828902._SY75_.jpg"}, {"title": "How to Read a Book: The Classic Guide to Intelligent Reading", "author": "Adler, Mortimer J.", "cover": "https://i.gr-assets.com/images/S/compressed.photo.goodreads.com/books/1310993739l/567610._SY75_.jpg"}, {"title": "The Bed of Procrustes: Philosophical and Practical Aphorisms (Incerto)", "author": "Taleb, Nassim Nicholas", "cover": "https://i.gr-assets.com/images/S/compressed.photo.goodreads.com/books/1665067245l/9402297._SY75_.jpg"}, {"title": "Skin in the Game: The Hidden Asymmetries in Daily Life", "author": "Taleb, Nassim Nicholas", "cover": "https://i.gr-assets.com/images/S/compressed.photo.goodreads.com/books/1510319798l/36064445._SY75_.jpg"}, {"title": "Antifragile: Things That Gain from Disorder", "author": "Taleb, Nassim Nicholas", "cover": "https://i.gr-assets.com/images/S/compressed.photo.goodreads.com/books/1352422827l/13530973._SY75_.jpg"}, {"title": "The Black Swan: The Impact of the Highly Improbable", "author": "Taleb, Nassim Nicholas", "cover": "https://i.gr-assets.com/images/S/compressed.photo.goodreads.com/books/1386925471l/242472._SY75_.jpg"}, {"title": "The Mind is Flat: The Illusion of Mental Depth and The Improvised Mind", "author": "Chater, Nick", "cover": "https://i.gr-assets.com/images/S/compressed.photo.goodreads.com/books/1515861260l/37926707._SY75_.jpg"}, {"title": "Optionality: How to Survive and Thrive in a Volatile World", "author": "Meadows, Richard", "cover": "https://i.gr-assets.com/images/S/compressed.photo.goodreads.com/books/1678228400l/123202416._SX50_.jpg"}, {"title": "Hackers and Painters", "author": "Graham, Paul", "cover": "https://i.gr-assets.com/images/S/compressed.photo.goodreads.com/books/1348562702l/41793._SY75_.jpg"}]